fspath/__init__.py
fspath/__pkginfo__.py
fspath/_which.py
fspath/cli.py
fspath/compat.py
fspath/console.py
fspath/debug.py
fspath/fspath.py
fspath/helper.py
fspath/main.py
fspath/os_env.py
fspath/progressbar.py
fspath/sui.py
fspath/win.py
lib/fspath/__init__.py
lib/fspath/__pkginfo__.py
lib/fspath/_which.py
lib/fspath/cli.py
lib/fspath/compat.py
lib/fspath/console.py
lib/fspath/debug.py
lib/fspath/fspath.py
lib/fspath/helper.py
lib/fspath/main.py
lib/fspath/os_env.py
lib/fspath/progressbar.py
lib/fspath/sui.py
lib/fspath/win.py
fspath-20230629.dist-info/LICENSE
fspath-20230629.dist-info/METADATA
fspath-20230629.dist-info/WHEEL
fspath-20230629.dist-info/entry_points.txt
fspath-20230629.dist-info/top_level.txt
fspath-20230629.dist-info/RECORD
