Metadata-Version: 2.1
Name: fspath
Version: 20230629
Summary: semantic path names and more
Home-page: https://github.com/return42/fspath
Author: Markus Heiser
Author-email: markus.heiser@darmarIT.de
License: AGPLv3
Keywords: path-names development
Classifier: Development Status :: 5 - Production/Stable
Classifier: Intended Audience :: Developers
Classifier: License :: OSI Approved :: GNU Affero General Public License v3 or later (AGPLv3+)
Classifier: Operating System :: OS Independent
Classifier: Programming Language :: Python
Classifier: Programming Language :: Python :: 2
Classifier: Programming Language :: Python :: 3
Classifier: Topic :: Utilities
Classifier: Topic :: Software Development :: Libraries
Classifier: Topic :: System :: Filesystems
License-File: LICENSE
Requires-Dist: six
